stockquant/__init__.py
stockquant/backtest.py
stockquant/config.py
stockquant/indicators.py
stockquant/market.py
stockquant/quant.py
stockquant/tick.py
stockquant/trade.py
stockquant/source/__init__.py
stockquant/source/baostockdata.py
stockquant/source/money.py
stockquant/source/sinadata.py
stockquant/source/tusharedata.py
stockquant/utils/__init__.py
stockquant/utils/dingtalk.py
stockquant/utils/logger.py
stockquant/utils/sendmail.py
stockquant/utils/storage.py
stockquant/utils/tools.py
stockquant-1.2.0.dist-info/METADATA
stockquant-1.2.0.dist-info/WHEEL
stockquant-1.2.0.dist-info/top_level.txt
stockquant-1.2.0.dist-info/RECORD
