Metadata-Version: 2.1
Name: stockquant
Version: 1.2.0
Summary: Professional quant framework
Home-page: https://github.com/Gary-Hertel/StockQuant
Author: Gary-Hertel
Author-email: garyhertel@foxmail.com
License: MIT
Keywords: stockquant,quant,framework
Platform: any
Requires-Dist: numpy
Requires-Dist: requests
Requires-Dist: concurrent-log-handler
Requires-Dist: colorlog
Requires-Dist: pandas
Requires-Dist: matplotlib
Requires-Dist: tushare
Requires-Dist: baostock
Requires-Dist: easytrader
